AUTHOR
LICENSE
MANIFEST.in
README.rst
setup.cfg
setup.py
pypreclin/__init__.py
pypreclin/configure.py
pypreclin/info.py
pypreclin.egg-info/PKG-INFO
pypreclin.egg-info/SOURCES.txt
pypreclin.egg-info/dependency_links.txt
pypreclin.egg-info/requires.txt
pypreclin.egg-info/top_level.txt
pypreclin/apps/__init__.py
pypreclin/apps/pypreclin_config.json
pypreclin/apps/pypreclinview
pypreclin/plotting/__init__.py
pypreclin/plotting/check_preprocessing.py
pypreclin/preproc/__init__.py
pypreclin/preproc/jip_controller.py
pypreclin/preproc/register.py
pypreclin/preproc/undist.py
pypreclin/preproc/resources/apply_inv_nonlin.com
pypreclin/preproc/resources/apply_nonlin.com
pypreclin/scripts/pypreclin_prepare_target
pypreclin/scripts/pypreclin_preproc_fmri
pypreclin/scripts/pypreclin_preproc_multi_fmri
pypreclin/utils/__init__.py
pypreclin/utils/affine.py
pypreclin/utils/export.py
pypreclin/utils/filetools.py
pypreclin/utils/quaternions.py
pypreclin/utils/reorient.py
pypreclin/utils/resources/pypreclin_qcpreproc.json
pypreclin/workflow/__init__.py
pypreclin/workflow/preproc_fmri.py