Metadata-Version: 2.1
Name: pypreclin
Version: 1.0.1
Summary: 
